data_sniffer/__init__.py
data_sniffer/apps.py
data_sniffer/constants.py
data_sniffer/errors.py
data_sniffer/tasks.py
data_sniffer/urls.py
data_sniffer/utils.py
data_sniffer/views.py
data_sniffer/static/data_sniffer/css/style.css
data_sniffer/templates/data_sniffer/empty.html
data_sniffer/templates/data_sniffer/invalid.html
data_sniffer/templates/data_sniffer/row.html
data_sniffer/templates/data_sniffer/status.html
data_sniffer/templatetags/__init__.py
data_sniffer/templatetags/index.py
django_data_sniffer-0.4.2.dist-info/METADATA
django_data_sniffer-0.4.2.dist-info/RECORD
django_data_sniffer-0.4.2.dist-info/WHEEL
django_data_sniffer-0.4.2.dist-info/top_level.txt
