Metadata-Version: 2.1
Name: django-data-sniffer
Version: 0.4.2
Summary: Sniff your django models to look for any data issues
Home-page: https://github.com/thefedoration/django-data-sniffer/
Author: Fedor Garin
Author-email: fedor.garin@gmail.com
License: MIT
Platform: UNKNOWN
Requires-Dist: Django (<1.8,>=1.7)
Requires-Dist: requests
